<persistence xmlns="http://xmlns.jcp.org/xml/ns/persistence" xmlns:xsi="http://www.w3.org/2001/XMLSchema-instance"
  xsi:schemaLocation="http://xmlns.jcp.org/xml/ns/persistence
http://xmlns.jcp.org/xml/ns/persistence/persistence_2_1.xsd"
  version="2.1">
  <persistence-unit name="mavenJPA" transaction-type="RESOURCE_LOCAL">
  <provider>org.hibernate.jpa.HibernatePersistenceProvider</provider>
  <properties>
    <property name="javax.persistence.jdbc.url" value="jdbc:oracle:thin:@t5tstsede-scan.sg.gbs.pro:1521/OTH_ORABE.bsella.it" />
    <property name="javax.persistence.jdbc.user" value="svil_team65" />
    <property name="javax.persistence.jdbc.password" value="temp_123" />
    <property name="javax.persistence.jdbc.driver" value="oracle.jdbc.driver.OracleDriver" />
    <property name="hibernate.show_sql" value="true" />
    <property name="hibernate.format_sql" value="true" />
    <property name="hibernate.dialect" value="org.hibernate.dialect.Oracle10gDialect" />
    <property name="hibernate.hbm2ddl.auto" value="create" />
   </properties>
  </persistence-unit>
</persistence>